MANIFEST.in
README.rst
pi_naming.py
setup.cfg
setup.py
pi_naming.egg-info/PKG-INFO
pi_naming.egg-info/SOURCES.txt
pi_naming.egg-info/dependency_links.txt
pi_naming.egg-info/entry_points.txt
pi_naming.egg-info/not-zip-safe
pi_naming.egg-info/top_level.txt