Metadata-Version: 1.1
Name: pi-naming
Version: 1.0.0
Summary: Check PI naming conventions, plugin for flake8
Home-page: https://github.com/561546441/pi-naming.git
Author: huang kh
Author-email: 561546441@qq.com
License: Expat license
Keywords: pi naming
Platform: UNKNOWN
Classifier: Development Status :: 3 - Alpha
Classifier: Environment :: Console
Classifier: Intended Audience :: Developers
Classifier: License :: OSI Approved :: MIT License
Classifier: Operating System :: OS Independent
Classifier: Programming Language :: Python
Classifier: Programming Language :: Python :: 2
Classifier: Programming Language :: Python :: 3
Classifier: Topic :: Software Development :: Libraries :: Python Modules
Classifier: Topic :: Software Development :: Quality Assurance
